{
  "width": 1200,
  "height": 675,
  "aspect_ratio": 1.778,
  "file_size_kb": 155.6,
  "hero_eligible": false,
  "card_eligible": true,
  "hires_eligible": false,
  "computed_at": "2026-05-20T14:12:21.083412+00:00",
  "derivative_width": 1200,
  "derivative_height": 675,
  "hero_photo_quality_score": 60,
  "has_text_overlay": false,
  "has_marketing_overlay": null,
  "winning_url": "https://d2p0bx8wfdkjkb.cloudfront.net/static/properties/78N8EQQ9DP/TVT5GBUEKW/zEdz37nuHx/EB-RP2940.jpeg",
  "candidate_count": 5,
  "picker_excluded_count": 0,
  "repicked_at": "2026-05-20T14:12:21.086814+00:00"
}
