{
  "width": 1200,
  "height": 699,
  "aspect_ratio": 1.717,
  "file_size_kb": 144.6,
  "hero_eligible": false,
  "card_eligible": true,
  "hires_eligible": false,
  "computed_at": "2026-05-19T13:05:03.382583+00:00",
  "hero_photo_quality_score": 60,
  "has_text_overlay": false,
  "winning_url": "https://assets.easybroker.com/property_images/4555331/76431990/EB-QM5331.jpg?rasterize=true&version=1718736000",
  "candidate_count": 5,
  "picker_excluded_count": 1,
  "repicked_at": "2026-05-19T13:05:03.382751+00:00"
}
