{
  "width": 1440,
  "height": 1080,
  "aspect_ratio": 1.333,
  "file_size_kb": 528.8,
  "hero_eligible": false,
  "card_eligible": true,
  "hires_eligible": true,
  "computed_at": "2026-05-19T13:27:44.715425+00:00",
  "hero_photo_quality_score": 100,
  "has_text_overlay": false,
  "winning_url": "https://remaxcaribbeanandcentralamerica.azureedge.net/images/002284071009/v3/HDPhotos/IMG_0293.jpeg",
  "candidate_count": 1,
  "picker_excluded_count": 0,
  "repicked_at": "2026-05-19T13:27:44.715664+00:00"
}
